HISTORY
MANIFEST.in
README.rst
setup.py
django_simplegallery.egg-info/PKG-INFO
django_simplegallery.egg-info/SOURCES.txt
django_simplegallery.egg-info/dependency_links.txt
django_simplegallery.egg-info/not-zip-safe
django_simplegallery.egg-info/requires.txt
django_simplegallery.egg-info/top_level.txt
simplegallery/__init__.py
simplegallery/admin.py
simplegallery/cms_plugins.py
simplegallery/fields.py
simplegallery/models.py
simplegallery/south_introspections.py
simplegallery/media/css/simplegallery.css
simplegallery/media/js/jquery.simplegallery.js
simplegallery/migrations/0001_initial.py
simplegallery/migrations/0002_add_groups.py
simplegallery/migrations/0003_auto__add_field_gallerypublication_raw_aspect_ratio.py
simplegallery/migrations/0004_auto__add_field_gallerytranslation_drop_up_label.py
simplegallery/migrations/0005_auto__del_field_gallerytranslation_drop_up_label.py
simplegallery/migrations/0006_fix_null_on_textfields_1of2.py
simplegallery/migrations/0007_fix_null_on_textfields_2of2.py
simplegallery/migrations/0008_auto__add_field_image_free_link__add_field_carouselimage_free_link.py
simplegallery/migrations/0009_auto__del_field_carouselimage_title_2__del_field_carouselimage_descrip.py
simplegallery/migrations/0010_auto__chg_field_image_free_link__chg_field_carouselimage_free_link.py
simplegallery/migrations/0011_auto__add_field_gallery_folder.py
simplegallery/migrations/__init__.py
simplegallery/templates/simplegallery/gallery_lite.html
simplegallery/templates/simplegallery/gallery_plugin.html
simplegallery/templates/simplegallery/plugin_form.html