Metadata-Version: 1.1
Name: django-simplegallery
Version: 0.13
Summary: django image gallery app
Home-page: http://github.com/divio/django-simplegallery/
Author: Stefan Foulis
Author-email: UNKNOWN
License: UNKNOWN
Platform: OS Independent
Classifier: Environment :: Web Environment
Classifier: Framework :: Django
Classifier: Intended Audience :: Developers
Classifier: License :: OSI Approved :: BSD License
Classifier: Operating System :: OS Independent
Classifier: Programming Language :: Python
Classifier: Topic :: Internet :: WWW/HTTP :: Dynamic Content
Classifier: Topic :: Software Development
Classifier: Topic :: Software Development :: Libraries :: Application Frameworks
Classifier: Development Status :: 5 - Production/Stable
Requires: django (<1.2.5)
Requires: mptt (<0.4)
Requires: django_cms
Requires: django_filer
Requires: django_multilingual_ng
Requires: django_tinymce
